lazyutils/__init__.py
lazyutils/config/Configuration.py
lazyutils/config/__init__.py
lazyutils/file/TempWritableFile.py
lazyutils/file/__init__.py
lazyutils/misc/Dates.py
lazyutils/misc/__init__.py
lazyutils/persistance/IPersistance.py
lazyutils/persistance/Local.py
lazyutils/persistance/Persistance.py
lazyutils/persistance/Rbdms.py
lazyutils/persistance/__init__.py
lazyutils/random/Randomize.py
lazyutils/random/__init__.py
lazyutils/secrets/ISecrets.py
lazyutils/secrets/LocalSecrets.py
lazyutils/secrets/Secrets.py
lazyutils/secrets/SecretsException.py
lazyutils/secrets/__init__.py
lazyutils/structure/Callable.py
lazyutils/structure/Singleton.py
lazyutils/structure/__init__.py
lazydev_utils-0.1.6.dist-info/LICENSE
lazydev_utils-0.1.6.dist-info/METADATA
lazydev_utils-0.1.6.dist-info/WHEEL
lazydev_utils-0.1.6.dist-info/top_level.txt
lazydev_utils-0.1.6.dist-info/RECORD
