Metadata-Version: 2.1
Name: lazydev-utils
Version: 0.1.6
Summary: Lazy utils with broad different function to improve python implementation
Home-page: UNKNOWN
Author: Paulo Born
License: MIT
Platform: UNKNOWN
Classifier: Programming Language :: Python :: 3
Classifier: License :: OSI Approved :: MIT License
Classifier: Operating System :: OS Independent
Requires-Python: >=3.6
Requires-Dist: pandas (>=1.1.4)
